{
    "catalog": [
        {
            "name": "Cesium 3D Tiles",
            "type": "group",
            "items": [
                {
                    "name": "Example enwtine 3d tiles",
                    "type": "3d-tiles",
                    "url": "http://cesium.entwine.io/data/nyc-2/tileset.json",
                    "options": {
                        "maximumScreenSpaceError": 1,
                        "maximumNumberOfLoadedTiles": 1000
                    }
                }
            ]
        }
    ]
}
